{
 "actions": [],
 "allow_rename": 1,
 "creation": "2025-07-16 15:51:08.159354",
 "doctype": "DocType",
 "editable_grid": 1,
 "engine": "InnoDB",
 "field_order": [
  "normal_sangat",
  "special_sangat",
  "ladies_sangat",
  "bal_sangat",
  "column_break_gzov",
  "english_sangat",
  "average_monthly",
  "monthly_building"
 ],
 "fields": [
  {
   "columns": 1,
   "fieldname": "normal_sangat",
   "fieldtype": "Int",
   "in_list_view": 1,
   "label": "Normal Sangat\t"
  },
  {
   "columns": 1,
   "fieldname": "special_sangat",
   "fieldtype": "Int",
   "in_list_view": 1,
   "label": "Special Sangat\t"
  },
  {
   "columns": 1,
   "fieldname": "ladies_sangat",
   "fieldtype": "Int",
   "in_list_view": 1,
   "label": "Ladies Sangat\t"
  },
  {
   "columns": 2,
   "fieldname": "average_monthly",
   "fieldtype": "Int",
   "in_list_view": 1,
   "label": "Average Monthly Namaskar"
  },
  {
   "columns": 2,
   "fieldname": "monthly_building",
   "fieldtype": "Int",
   "in_list_view": 1,
   "label": "Monthly Building Fund"
  },
  {
   "columns": 1,
   "fieldname": "bal_sangat",
   "fieldtype": "Int",
   "in_list_view": 1,
   "label": "Bal Sangat"
  },
  {
   "columns": 2,
   "fieldname": "english_sangat",
   "fieldtype": "Int",
   "in_list_view": 1,
   "label": "English Sangat\t"
  },
  {
   "fieldname": "column_break_gzov",
   "fieldtype": "Column Break"
  }
 ],
 "grid_page_length": 50,
 "index_web_pages_for_search": 1,
 "istable": 1,
 "links": [],
 "modified": "2025-08-01 11:25:22.907932",
 "modified_by": "Administrator",
 "module": "Building Construction Manufacturing Service",
 "name": "DETAILS OF SANGAT",
 "owner": "Administrator",
 "permissions": [],
 "row_format": "Dynamic",
 "sort_field": "modified",
 "sort_order": "DESC",
 "states": []
}